pysubstringsearch-0.7.1.dist-info/METADATA
pysubstringsearch-0.7.1.dist-info/WHEEL
pysubstringsearch/py.typed
pysubstringsearch/pysubstringsearch.pyi
pysubstringsearch/__init__.py
pysubstringsearch/pysubstringsearch.pyd
pysubstringsearch-0.7.1.dist-info/RECORD
