Metadata-Version: 2.1
Name: pysubstringsearch
Version: 0.7.1
Summary: A Python library written in Rust that searches for substrings quickly using a Suffix Array
Keywords: substring,pattern,search,suffix,array,rust,pyo3
Home-Page: https://github.com/intsights/pysubstringsearch
Author: Gal Ben David <gal@intsights.com>
Author-email: Gal Ben David <gal@intsights.com>
License: MIT
Project-URL: Source Code, https://github.com/intsights/pysubstringsearch
